{
  "order": "xm-12132",
  "db_path": "/Users/chen/Library/Application Support/Trae CN/User/workspaceStorage/17ed86c50d0af8f5ed25b3eb5fd38be5/state.vscdb",
  "sessionId": "69f4c9a8d914953fdbe298f2",
  "rows": [
    {
      "sessionId": ".3792634309254663:3fafa05c52e6e8d6fdd1934d4bbccefd_69f4c9a8d914953fdbe298f2.69f4ca6cd914953fdbe299e3.69f4ca6af9caab72051041fd:Trae CN.T(2026/5/1 18:44:44)",
      "rawSessionId": "69f4c9a8d914953fdbe298f2",
      "conversation": "请按游戏任务与成就系统的业务对象展开，让用户操作能沉淀为后续可查询的业务证据，确保后续开发、联调和验收有同一套依据。业务中台、单体或轻量服务的取舍可按你的理解处理，但要让角色工作台、状态机和审计日志彼此连贯，不要把复杂业务压成普通 CRUD。\n先定义任务配置、触发事件、进度、成就、奖励、埋点之间的字段关系，再定义玩家、策划、运营、客服的可见范围和可操作按钮；业务流程从配置任务 -> 玩家触发 -> 进度累计 -> 达成奖励 -> 数据分析逐步推进，关键状态包括待配置任务、待玩家触发、待进度累计、待达成奖励、待数据分析。\n\n\n报表侧需要把处理时长、转化结果、异常比例和收益口径拆清楚，支持回查明细来源，并回到游戏任务与成就系统的主单台账中校验。\n组件约束：不要生成容器化配置或非必要外部服务，数据库默认优先使用 SQLite 文件数据库（例如 data/app.sqlite）以最快打通完整业务链路；如果业务确实强依赖 MySQL、PostgreSQL、Redis、消息队列或对象存储等特定组件，可以引入，但必须说明依赖原因、配置入口、启动方式和本地降级方案。\n端口约束：前后端端口必须优先围绕项目目录名称中的数字本身规划，但端口号必须是 0 到 65535 之间的合法数字。四位项目号例如 xm-8744，端口必须包含 8744，可使用 87441、87442 或 18744、28744 这类合法前后缀组合；五位项目号例如 xm-11132，不能拼成 111321 这类超过 65535 的非法端口，必须取后四位 1132 作为端口前后缀，可使用 11132、21132、11321、11322 等合法端口；若目录数字较短，可使用该数字补位后加 01/02（如 xm-71 使用 7101/7102）。统一写入 .env 或配置文件，并同步 CORS、代理和回调地址，避开 3000、5173、8000、8080 等常见端口。\n验收约束：完成代码后必须实际启动后端和前端，打印访问地址，并通过关键页面操作和接口请求验证主业务链路已调通。\n前后端启动方式统一使用后台启动，关闭终端不影响程序运行，只有手动关闭对应端口进程才算完成关闭。\n\n不要提问我问题，遇到脚本问题、执行问题、权限问题等都允许你自行解决。\n\n在执行阶段，涉及项目内删除操作时无需再征求我的同意。\n\n按照需求功能的顺序，每一轮都优先考虑搭建核心功能，在逐步的考虑其他功能。",
      "logTrace": ".3792634309254663:3fafa05c52e6e8d6fdd1934d4bbccefd_69f4c9a8d914953fdbe298f2.69f4ca6cd914953fdbe299e3.69f4ca6af9caab72051041fd:Trae CN.T(2026/5/1 18:44:44)"
    },
    {
      "sessionId": ".3792634309254663:3953e38ab78514e7b197944643c73911_69f4c9a8d914953fdbe298f2.69f4cf6685d83e4a45ef7168.69f4cf66ac72118055fd1055:Trae CN.T(2026/5/1 19:05:58)",
      "rawSessionId": "69f4c9a8d914953fdbe298f2",
      "conversation": "运行时间过长。第二轮请优化并完成任务。",
      "logTrace": ".3792634309254663:3953e38ab78514e7b197944643c73911_69f4c9a8d914953fdbe298f2.69f4cf6685d83e4a45ef7168.69f4cf66ac72118055fd1055:Trae CN.T(2026/5/1 19:05:58)"
    },
    {
      "sessionId": ".3792634309254663:b148bc559c4c6aa4abdf706ecb3a4a9b_69f4c9a8d914953fdbe298f2.69f4fa1e85d83e4a45ef76d8.69f4fa1dac72118055fd1056:Trae CN.T(2026/5/1 22:08:14)",
      "rawSessionId": "69f4c9a8d914953fdbe298f2",
      "conversation": "登录存在问题，最后一轮。",
      "logTrace": ".3792634309254663:b148bc559c4c6aa4abdf706ecb3a4a9b_69f4c9a8d914953fdbe298f2.69f4fa1e85d83e4a45ef76d8.69f4fa1dac72118055fd1056:Trae CN.T(2026/5/1 22:08:14)"
    }
  ],
  "cached": true,
  "refreshedAt": "2026-05-01T22:25:20"
}
