{
  "order": "xm-11151",
  "db_path": "/Users/chen/Library/Application Support/Trae CN/User/workspaceStorage/47e574084658827b7577faf45d01597f/state.vscdb",
  "sessionId": "69f45e72647bbcfa469a33d5",
  "rows": [
    {
      "sessionId": ".3792634309254663:8d3e75413ead353faa353c28989849aa_69f45e72647bbcfa469a33d5.69f45e7e647bbcfa469a33d7.69f45e790c19357d099353a3:Trae CN.T(2026/5/1 11:04:14)",
      "rawSessionId": "69f45e72647bbcfa469a33d5",
      "conversation": "交付智慧公交调度系统前，围绕责任划分、风险控制和效率统计展开，便于后续扩展审批、复核、导出和看板。组件、服务和状态管理方式请按场景合理发挥，只要保证核心流程能跑通、关键状态可追踪，不要为了形式统一而削弱业务表达。\n从数据、权限、规则和状态四条线展开，第一层是线路、班次、车辆轨迹、站点、到站预测、告警等核心数据，第二层是调度员、司机、乘客、运营、维修的岗位权限，第三层是运力匹配与路径成本引擎、轨迹验真与异常停留检测引擎、分段计费与回单核验引擎、线路规则引擎，第四层是按“排班发车 -> 车辆运行 -> 到站预测 -> 异常调度 -> 运营统计”流转的状态机。\n\n- 调度员在前端排班发车，填写线路相关字段、附件、责任人和期望完成时间，后端生成主单号、明细表、初始状态与待办消息，并校验必填项、重复单和权限边界。\n- 当流程推进到车辆运行，后端要根据班次计算校验结果，前端展示通过、驳回、补充资料、转派四类动作，并把审批意见沉淀到时间轴。\n- 对应责任人接收待办后执行到站预测，前端展示当前可用动作，后端依据车辆轨迹、上一节点结果和业务规则推进到“待到站预测”状态，同时写入操作日志。\n- 进入异常调度节点时，系统需要锁定相关站点，避免多端并发修改；处理结果提交后，后端同步刷新看板、通知相关角色并生成下一步责任人。\n- 运营统计不能只改页面文案，必须更新主单状态、明细状态、消息状态和统计口径，确保对应角色看到的待办数量与数据库事实一致。\n- 定位漂移、路线偏离、司机拒接、到达未确认或第三方地图回调延迟时，系统要进入异常队列，保留原始轨迹和补偿计算依据，并回到智慧公交调度系统的主单台账中校验。\n- 围绕验收目标“实现车辆地图、修复到站 ETA、增加班次调度、测试告警”，测试用例要覆盖正常流、驳回流、撤销流、超时流、重复提交、接口失败和历史数据迁移，确保前后端字段、状态和报表口径一致。\n\n在智慧公交调度系统中，验收时至少覆盖新增、编辑、提交、撤回、审核、执行、异常、关闭、导出九类用例，数据库必须保留状态变更前后值、操作者、时间戳、来源端和关联单据。\n组件约束：不要生成容器化配置或非必要外部服务，数据库默认优先使用 SQLite 文件数据库（例如 data/app.sqlite）以最快打通完整业务链路；如果业务确实强依赖 MySQL、PostgreSQL、Redis、消息队列或对象存储等特定组件，可以引入，但必须说明依赖原因、配置入口、启动方式和本地降级方案。\n端口约束：前后端端口必须优先围绕项目目录名称中的数字本身规划，但端口号必须是 0 到 65535 之间的合法数字。四位项目号例如 xm-8744，端口必须包含 8744，可使用 87441、87442 或 18744、28744 这类合法前后缀组合；五位项目号例如 xm-11132，不能拼成 111321 这类超过 65535 的非法端口，必须取后四位 1132 作为端口前后缀，可使用 11132、21132、11321、11322 等合法端口；若目录数字较短，可使用该数字补位后加 01/02（如 xm-71 使用 7101/7102）。统一写入 .env 或配置文件，并同步 CORS、代理和回调地址，避开 3000、5173、8000、8080 等常见端口。\n验收约束：完成代码后必须实际启动后端和前端，打印访问地址，并通过关键页面操作和接口请求验证主业务链路已调通。\n前后端启动方式统一使用后台启动，关闭终端不影响程序运行，只有手动关闭对应端口进程才算完成关闭。\n\n不要提问我问题，遇到脚本问题、执行问题、权限问题等都允许你自行解决。\n\n默认授权你在执行过程中直接做项目内删除，不需要我二次批准。\n\n按照需求功能的顺序，每一轮都优先考虑搭建核心功能，在逐步的考虑其他功能。",
      "logTrace": "",
      "logTraceId": ".3792634309254663:8d3e75413ead353faa353c28989849aa_69f45e72647bbcfa469a33d5.69f45e7e647bbcfa469a33d7.69f45e790c19357d099353a3:Trae CN.T(2026/5/1 11:04:14)",
      "sessionComposite": ".3792634309254663:8d3e75413ead353faa353c28989849aa_69f45e72647bbcfa469a33d5.69f45e7e647bbcfa469a33d7.69f45e790c19357d099353a3:Trae CN.T(2026/5/1 11:04:14)",
      "logTraceSource": "not-found-real-file",
      "logTraceSourceDetail": "/Users/chen/Library/Application Support/Trae CN/User/workspaceStorage/47e574084658827b7577faf45d01597f/state.vscdb",
      "logTraceReconstructed": false,
      "officialCopiedLogTrace": false,
      "logTraceMissing": [
        "official_copied_text_not_found_in_local_storage"
      ],
      "logTraceReconstructionVersion": "20260509_v9_real_only"
    },
    {
      "sessionId": ".3792634309254663:c16c56c193ed64117c1f7163e0ff0e77_69f45e72647bbcfa469a33d5.69f462d7d914953fdbe278e5.69f462d7ac61ce79963119c2:Trae CN.T(2026/5/1 11:22:47)",
      "rawSessionId": "69f45e72647bbcfa469a33d5",
      "conversation": "运行时间太长了。请继续完成业务目标",
      "logTrace": "",
      "logTraceId": ".3792634309254663:c16c56c193ed64117c1f7163e0ff0e77_69f45e72647bbcfa469a33d5.69f462d7d914953fdbe278e5.69f462d7ac61ce79963119c2:Trae CN.T(2026/5/1 11:22:47)",
      "sessionComposite": ".3792634309254663:c16c56c193ed64117c1f7163e0ff0e77_69f45e72647bbcfa469a33d5.69f462d7d914953fdbe278e5.69f462d7ac61ce79963119c2:Trae CN.T(2026/5/1 11:22:47)",
      "logTraceSource": "not-found-real-file",
      "logTraceSourceDetail": "/Users/chen/Library/Application Support/Trae CN/User/workspaceStorage/47e574084658827b7577faf45d01597f/state.vscdb",
      "logTraceReconstructed": false,
      "officialCopiedLogTrace": false,
      "logTraceMissing": [
        "official_copied_text_not_found_in_local_storage"
      ],
      "logTraceReconstructionVersion": "20260509_v9_real_only"
    },
    {
      "sessionId": ".3792634309254663:87da356e7265d0916f33e89c5d1d524a_69f45e72647bbcfa469a33d5.69f46aeed914953fdbe27d16.69f46aeeac61ce79963119c3:Trae CN.T(2026/5/1 11:57:18)",
      "rawSessionId": "69f45e72647bbcfa469a33d5",
      "conversation": "没有完成高德地图 百度地图的api调用。无法完成业务目标。最后一轮请持续迭代。",
      "logTrace": "",
      "logTraceId": ".3792634309254663:87da356e7265d0916f33e89c5d1d524a_69f45e72647bbcfa469a33d5.69f46aeed914953fdbe27d16.69f46aeeac61ce79963119c3:Trae CN.T(2026/5/1 11:57:18)",
      "sessionComposite": ".3792634309254663:87da356e7265d0916f33e89c5d1d524a_69f45e72647bbcfa469a33d5.69f46aeed914953fdbe27d16.69f46aeeac61ce79963119c3:Trae CN.T(2026/5/1 11:57:18)",
      "logTraceSource": "not-found-real-file",
      "logTraceSourceDetail": "/Users/chen/Library/Application Support/Trae CN/User/workspaceStorage/47e574084658827b7577faf45d01597f/state.vscdb",
      "logTraceReconstructed": false,
      "officialCopiedLogTrace": false,
      "logTraceMissing": [
        "official_copied_text_not_found_in_local_storage"
      ],
      "logTraceReconstructionVersion": "20260509_v9_real_only"
    }
  ],
  "cached": true,
  "refreshedAt": "2026-05-01T15:11:42",
  "logTraceMode": "real-official-copy-only",
  "logTraceVersion": "20260509_v9_1_real_only"
}
