{
  "order": "xm-20776",
  "db_path": "/Users/chen/Library/Application Support/Trae CN/User/workspaceStorage/22bebcc203c26f7d419a22d477854764/state.vscdb",
  "sessionId": "69f7db887f0ec5291f1c7fae",
  "rows": [
    {
      "sessionId": ".3792634309254663:b98bb533a06b96aa8f32c727a70c55f8_69f7db887f0ec5291f1c7fae.69f7db9a7f0ec5291f1c7fb0.69f7db995b430e46be37a1a3:Trae CN.T(2026/5/4 02:34:49)",
      "rawSessionId": "69f7db887f0ec5291f1c7fae",
      "conversation": "去哪儿用户积分成长体系要按真实业务项目落地成 Web 全栈系统，先围绕角色、对象、页面、动作、状态和数据闭环实现核心链路，不要写成静态展示页。\n去哪儿用户中心积分成长值体系要把全站消费、支付中心、用户中心和业务线优惠打通，让老用户的持续消费沉淀成积分、成长等级和可使用的等级特权。\n1. 业务线在用户消费完成后调用支付中心发放积分，支付中心从业务线积分账户扣减并记录积分流水，再把订单信息透传给用户中心计算成长值。\n2. 积分按消费行为和业务线自定义系数发放，可用于积分商城兑换；成长值只按消费金额和固定业务线系数计算，用于小骆驼、铜骆驼、银骆驼、金骆驼等级判断。\n3. 各业务线系数必须固定在用户中心口径中，酒店、机票、门票、火车票、用车、度假、团购、保险等业务线分别按不同权重累计成长值，业务线前台下单时读取用户等级展示差异化优惠。\n4. 支付中心记录流水时要同时记录用户等级优惠扣减信息，保证用户看到的等级、业务线优惠、支付金额和积分成长值入账能够相互解释。\n5. 用户中心页面需要展示积分、成长值、等级特权、成长值过期和保级策略，运营侧可按上线后三个月新增等级用户、积分发放量和特权使用频次评估效果。\n\n组件约束：不要生成容器化配置或非必要外部服务，数据库默认优先使用 SQLite 文件数据库（例如 data/app.sqlite）以最快打通完整业务链路；如果业务确实强依赖 MySQL、PostgreSQL、Redis、消息队列或对象存储等特定组件，可以引入，但必须说明依赖原因、配置入口、启动方式和本地降级方案。\n端口约束：前后端端口必须优先围绕项目目录名称中的数字本身规划，但端口号必须是 0 到 65535 之间的合法数字。五位项目号例如 xm-20768，不能拼成 207681 这类超过 65535 的非法端口，必须取后四位作为端口前后缀，可使用 20768、30768、07681、07682 等合法端口。统一写入 .env 或配置文件，并同步 CORS、代理和回调地址，避开 3000、5173、8000、8080 等常见端口。\n验收约束：完成代码后必须实际启动后端和前端，打印访问地址，并通过关键页面操作和接口请求验证主业务链路已调通。\n前后端启动方式统一使用后台启动，关闭终端不影响程序运行，只有手动关闭对应端口进程才算完成关闭。\n\n不要提问我问题，遇到脚本问题、执行问题、权限问题等都允许你自行解决。\n\n执行过程中，项目内的删除动作不需要经过我同意，可直接处理。\n\n按照需求功能的顺序，每一轮都优先考虑搭建核心功能，再逐步考虑其他功能。",
      "logTrace": "",
      "dissatisfactionReason": "服务不可用",
      "annotationHash": "cfe5d03558e3e0dc3efdde6d60b8574a64ebb756",
      "annotationVersion": "20260505_v6",
      "annotationUpdatedAt": "2026-05-05T13:39:17",
      "annotationSource": "next-row-direct",
      "logTraceId": ".3792634309254663:b98bb533a06b96aa8f32c727a70c55f8_69f7db887f0ec5291f1c7fae.69f7db9a7f0ec5291f1c7fb0.69f7db995b430e46be37a1a3:Trae CN.T(2026/5/4 02:34:49)",
      "sessionComposite": ".3792634309254663:b98bb533a06b96aa8f32c727a70c55f8_69f7db887f0ec5291f1c7fae.69f7db9a7f0ec5291f1c7fb0.69f7db995b430e46be37a1a3:Trae CN.T(2026/5/4 02:34:49)",
      "logTraceSource": "not-found-real-file",
      "logTraceSourceDetail": "/Users/chen/Library/Application Support/Trae CN/User/workspaceStorage/22bebcc203c26f7d419a22d477854764/state.vscdb",
      "logTraceReconstructed": false,
      "officialCopiedLogTrace": false,
      "logTraceMissing": [
        "official_copied_text_not_found_in_local_storage"
      ],
      "logTraceReconstructionVersion": "20260509_v9_real_only"
    },
    {
      "sessionId": ".3792634309254663:4f4c630451e7da019a47157ef3f09d73_69f7db887f0ec5291f1c7fae.69f84a567f0ec5291f1c8429.69f84a565b430e46be37a1a4:Trae CN.T(2026/5/4 10:27:18)",
      "rawSessionId": "69f7db887f0ec5291f1c7fae",
      "conversation": "服务不可用",
      "logTrace": "",
      "dissatisfactionReason": "金骆驼没有订单取消的选项",
      "annotationHash": "a345075e50a20bbf23f99dfbe2fac5288f0bb00b",
      "annotationVersion": "20260505_v6",
      "annotationUpdatedAt": "2026-05-05T13:39:17",
      "annotationSource": "next-row-direct",
      "logTraceId": ".3792634309254663:4f4c630451e7da019a47157ef3f09d73_69f7db887f0ec5291f1c7fae.69f84a567f0ec5291f1c8429.69f84a565b430e46be37a1a4:Trae CN.T(2026/5/4 10:27:18)",
      "sessionComposite": ".3792634309254663:4f4c630451e7da019a47157ef3f09d73_69f7db887f0ec5291f1c7fae.69f84a567f0ec5291f1c8429.69f84a565b430e46be37a1a4:Trae CN.T(2026/5/4 10:27:18)",
      "logTraceSource": "not-found-real-file",
      "logTraceSourceDetail": "/Users/chen/Library/Application Support/Trae CN/User/workspaceStorage/22bebcc203c26f7d419a22d477854764/state.vscdb",
      "logTraceReconstructed": false,
      "officialCopiedLogTrace": false,
      "logTraceMissing": [
        "official_copied_text_not_found_in_local_storage"
      ],
      "logTraceReconstructionVersion": "20260509_v9_real_only"
    },
    {
      "sessionId": ".3792634309254663:949095c2da242af0b25a8133868baf04_69f7db887f0ec5291f1c7fae.69f84c8c7f0ec5291f1c8552.69f84c8c5b430e46be37a1a5:Trae CN.T(2026/5/4 10:36:44)",
      "rawSessionId": "69f7db887f0ec5291f1c7fae",
      "conversation": "金骆驼没有订单取消的选项。",
      "logTrace": "",
      "dissatisfactionReason": "重复购买",
      "annotationHash": "20f0ad418006213e3d4c0e44948b049d7e07e3d7",
      "annotationVersion": "20260505_v6",
      "annotationUpdatedAt": "2026-05-05T13:39:17",
      "annotationSource": "next-row-direct",
      "logTraceId": ".3792634309254663:949095c2da242af0b25a8133868baf04_69f7db887f0ec5291f1c7fae.69f84c8c7f0ec5291f1c8552.69f84c8c5b430e46be37a1a5:Trae CN.T(2026/5/4 10:36:44)",
      "sessionComposite": ".3792634309254663:949095c2da242af0b25a8133868baf04_69f7db887f0ec5291f1c7fae.69f84c8c7f0ec5291f1c8552.69f84c8c5b430e46be37a1a5:Trae CN.T(2026/5/4 10:36:44)",
      "logTraceSource": "not-found-real-file",
      "logTraceSourceDetail": "/Users/chen/Library/Application Support/Trae CN/User/workspaceStorage/22bebcc203c26f7d419a22d477854764/state.vscdb",
      "logTraceReconstructed": false,
      "officialCopiedLogTrace": false,
      "logTraceMissing": [
        "official_copied_text_not_found_in_local_storage"
      ],
      "logTraceReconstructionVersion": "20260509_v9_real_only"
    },
    {
      "sessionId": ".3792634309254663:e655d4b16fcf93503fd6426f7d8a1319_69f7db887f0ec5291f1c7fae.69f855637f0ec5291f1c897b.69f855635b430e46be37a1a6:Trae CN.T(2026/5/4 11:14:27)",
      "rawSessionId": "69f7db887f0ec5291f1c7fae",
      "conversation": "同样的产品 尤其是机票不应该能重复购买。而且是同一时间的。",
      "logTrace": "",
      "dissatisfactionReason": "",
      "annotationHash": "d80ac602303eee62937ac59fadfb806ff8fda42a",
      "annotationVersion": "20260505_v6",
      "annotationUpdatedAt": "2026-05-05T13:39:17",
      "annotationSource": "next-row-empty",
      "logTraceId": ".3792634309254663:e655d4b16fcf93503fd6426f7d8a1319_69f7db887f0ec5291f1c7fae.69f855637f0ec5291f1c897b.69f855635b430e46be37a1a6:Trae CN.T(2026/5/4 11:14:27)",
      "sessionComposite": ".3792634309254663:e655d4b16fcf93503fd6426f7d8a1319_69f7db887f0ec5291f1c7fae.69f855637f0ec5291f1c897b.69f855635b430e46be37a1a6:Trae CN.T(2026/5/4 11:14:27)",
      "logTraceSource": "not-found-real-file",
      "logTraceSourceDetail": "/Users/chen/Library/Application Support/Trae CN/User/workspaceStorage/22bebcc203c26f7d419a22d477854764/state.vscdb",
      "logTraceReconstructed": false,
      "officialCopiedLogTrace": false,
      "logTraceMissing": [
        "official_copied_text_not_found_in_local_storage"
      ],
      "logTraceReconstructionVersion": "20260509_v9_real_only"
    }
  ],
  "cached": true,
  "refreshedAt": "2026-05-04T12:18:26",
  "logTraceMode": "real-official-copy-only",
  "logTraceVersion": "20260509_v9_1_real_only"
}
